[
  {
    "maxMem": "852468",
    "userTime": "21.82",
    "cpuUsage": "181%",
    "meta": {
      "commit": "ad22d5ac",
      "commitDate": "1713880914",
      "currentDate": "1714479509"
    }
  },
  {
    "maxMem": "946576",
    "userTime": "23.17",
    "cpuUsage": "185%",
    "meta": {
      "commit": "ad22d5ac",
      "commitDate": "1713880914",
      "currentDate": "1714480580"
    }
  },
  {
    "maxMem": "1007916",
    "userTime": "25.43",
    "cpuUsage": "268%",
    "meta": {
      "commit": "ad22d5ac",
      "commitDate": "1713880914",
      "currentDate": "1714491105"
    }
  },
  {
    "maxMem": "981228",
    "userTime": "24.78",
    "cpuUsage": "267%",
    "meta": {
      "commit": "6ac9aa74",
      "commitDate": "1714511016",
      "currentDate": "1714526747"
    }
  },
  {
    "maxMem": "1094684",
    "userTime": "25.33",
    "cpuUsage": "270%",
    "meta": {
      "commit": "6ac9aa74",
      "commitDate": "1714511016",
      "currentDate": "1714567026"
    }
  },
  {
    "maxMem": "1165204",
    "userTime": "26.71",
    "cpuUsage": "263%",
    "meta": {
      "commit": "6ac9aa74",
      "commitDate": "1714511016",
      "currentDate": "1714612813"
    }
  },
  {
    "maxMem": "1123744",
    "userTime": "26.26",
    "cpuUsage": "267%",
    "meta": {
      "commit": "1434292c",
      "commitDate": "1714642767",
      "currentDate": "1714653404"
    }
  },
  {
    "maxMem": "1029092",
    "userTime": "25.84",
    "cpuUsage": "274%",
    "meta": {
      "commit": "1434292c",
      "commitDate": "1714642767",
      "currentDate": "1714731661"
    }
  },
  {
    "maxMem": "944832",
    "userTime": "25.34",
    "cpuUsage": "268%",
    "meta": {
      "commit": "1434292c",
      "commitDate": "1714642767",
      "currentDate": "1714739707"
    }
  },
  {
    "maxMem": "962748",
    "userTime": "23.96",
    "cpuUsage": "263%",
    "meta": {
      "commit": "3099bd09",
      "commitDate": "1714742069",
      "currentDate": "1714742464"
    }
  },
  {
    "maxMem": "931208",
    "userTime": "24.71",
    "cpuUsage": "272%",
    "meta": {
      "commit": "3099bd09",
      "commitDate": "1714742069",
      "currentDate": "1714785597"
    }
  },
  {
    "maxMem": "1037832",
    "userTime": "24.71",
    "cpuUsage": "266%",
    "meta": {
      "commit": "3099bd09",
      "commitDate": "1714742069",
      "currentDate": "1714826061"
    }
  },
  {
    "maxMem": "1015676",
    "userTime": "26.19",
    "cpuUsage": "275%",
    "meta": {
      "commit": "3099bd09",
      "commitDate": "1714742069",
      "currentDate": "1714872348"
    }
  },
  {
    "maxMem": "971460",
    "userTime": "24.69",
    "cpuUsage": "267%",
    "meta": {
      "commit": "3099bd09",
      "commitDate": "1714742069",
      "currentDate": "1714912456"
    }
  },
  {
    "maxMem": "1032112",
    "userTime": "24.39",
    "cpuUsage": "265%",
    "meta": {
      "commit": "3099bd09",
      "commitDate": "1714742069",
      "currentDate": "1714958544"
    }
  },
  {
    "maxMem": "951956",
    "userTime": "25.09",
    "cpuUsage": "271%",
    "meta": {
      "commit": "3099bd09",
      "commitDate": "1714742069",
      "currentDate": "1714999026"
    }
  },
  {
    "maxMem": "915660",
    "userTime": "24.24",
    "cpuUsage": "270%",
    "meta": {
      "commit": "3127a70d",
      "commitDate": "1715004801",
      "currentDate": "1715044926"
    }
  },
  {
    "maxMem": "918976",
    "userTime": "25.83",
    "cpuUsage": "273%",
    "meta": {
      "commit": "3127a70d",
      "commitDate": "1715004801",
      "currentDate": "1715085366"
    }
  },
  {
    "maxMem": "991724",
    "userTime": "24.76",
    "cpuUsage": "267%",
    "meta": {
      "commit": "3127a70d",
      "commitDate": "1715004801",
      "currentDate": "1715130488"
    }
  },
  {
    "maxMem": "1030228",
    "userTime": "25.73",
    "cpuUsage": "264%",
    "meta": {
      "commit": "3127a70d",
      "commitDate": "1715004801",
      "currentDate": "1715171822"
    }
  },
  {
    "maxMem": "1043864",
    "userTime": "24.81",
    "cpuUsage": "265%",
    "meta": {
      "commit": "3127a70d",
      "commitDate": "1715004801",
      "currentDate": "1715217789"
    }
  }
]
